CHANGES.rst
CONTRIBUTORS.rst
MANIFEST.in
README.rst
setup.cfg
setup.py
docs/LICENSE.GPL
docs/LICENSE.rst
docs/index.rst
src/plonetheme/__init__.py
src/plonetheme.modernbase.egg-info/PKG-INFO
src/plonetheme.modernbase.egg-info/SOURCES.txt
src/plonetheme.modernbase.egg-info/dependency_links.txt
src/plonetheme.modernbase.egg-info/entry_points.txt
src/plonetheme.modernbase.egg-info/namespace_packages.txt
src/plonetheme.modernbase.egg-info/not-zip-safe
src/plonetheme.modernbase.egg-info/requires.txt
src/plonetheme.modernbase.egg-info/top_level.txt
src/plonetheme/modernbase/__init__.py
src/plonetheme/modernbase/configure.zcml
src/plonetheme/modernbase/interfaces.py
src/plonetheme/modernbase/setuphandlers.py
src/plonetheme/modernbase/testing.py
src/plonetheme/modernbase/browser/__init__.py
src/plonetheme/modernbase/browser/configure.zcml
src/plonetheme/modernbase/browser/overrides/.gitkeep
src/plonetheme/modernbase/browser/overrides/Products.CMFPlone.browser.templates.search.pt
src/plonetheme/modernbase/browser/overrides/Products.CMFPlone.skins.plone_templates.default_error_message.pt
src/plonetheme/modernbase/browser/overrides/Products.PloneFormGen.skins.PloneFormGen.fg_edit_macros_p3.pt
src/plonetheme/modernbase/browser/overrides/plone.app.contenttypes.behaviors.leadimage.pt
src/plonetheme/modernbase/browser/overrides/plone.app.contenttypes.browser.templates.listing.pt
src/plonetheme/modernbase/browser/overrides/plone.app.contenttypes.browser.templates.newsitem.pt
src/plonetheme/modernbase/browser/overrides/plone.batching.batchnavigation.pt
src/plonetheme/modernbase/browser/overrides/plone.portlet.collection.collection.pt
src/plonetheme/modernbase/browser/static/.gitkeep
src/plonetheme/modernbase/locales/plonetheme.clean-blog.pot
src/plonetheme/modernbase/locales/update.sh
src/plonetheme/modernbase/profiles/default/browserlayer.xml
src/plonetheme/modernbase/profiles/default/metadata.xml
src/plonetheme/modernbase/profiles/default/registry.xml
src/plonetheme/modernbase/profiles/default/theme.xml
src/plonetheme/modernbase/profiles/uninstall/browserlayer.xml
src/plonetheme/modernbase/profiles/uninstall/theme.xml
src/plonetheme/modernbase/tests/__init__.py
src/plonetheme/modernbase/tests/test_robot.py
src/plonetheme/modernbase/tests/test_setup.py
src/plonetheme/modernbase/tests/robot/test_example.robot
src/plonetheme/modernbase/theme/._LICENSE
