Metadata-Version: 1.1
Name: plonetheme.modernbase
Version: 0.1
Summary: An installable theme for Plone 5
Home-page: https://github.com/intk/plonetheme.modernbase
Author: Andre Goncalves
Author-email: andre@intk.com
License: GPL version 2
Keywords: Python Plone
Platform: UNKNOWN
Classifier: Environment :: Web Environment
Classifier: Framework :: Plone
Classifier: Framework :: Plone :: 5.0
Classifier: Programming Language :: Python
Classifier: Programming Language :: Python :: 2.7
Classifier: Operating System :: OS Independent
Classifier: License :: OSI Approved :: GNU General Public License v2 (GPLv2)
